openapi_client/__init__.py
openapi_client/api_client.py
openapi_client/api_response.py
openapi_client/configuration.py
openapi_client/exceptions.py
openapi_client/py.typed
openapi_client/rest.py
openapi_client/api/__init__.py
openapi_client/api/board_api.py
openapi_client/models/__init__.py
openapi_client/models/component_dto.py
openapi_client/models/create_board_dto.py
openapi_client/models/delete_board_dto.py
openapi_client/models/delete_board_item_dto.py
openapi_client/models/status_dto.py
openapi_client/models/template_dto.py
openapi_client/models/update_board_dto.py
openapi_client/models/update_board_item_dto.py
openapi_client/models/update_status_dto.py
openapi_client/models/update_status_dto0.py
openapi_client/models/update_table_component_from_agent.py
test/__init__.py
test/test_board_api.py
test/test_component_dto.py
test/test_create_board_dto.py
test/test_delete_board_dto.py
test/test_delete_board_item_dto.py
test/test_status_dto.py
test/test_template_dto.py
test/test_update_board_dto.py
test/test_update_board_item_dto.py
test/test_update_status_dto.py
test/test_update_table_component_from_agent.py
zedblock_client-1.0.0.dist-info/METADATA
zedblock_client-1.0.0.dist-info/WHEEL
zedblock_client-1.0.0.dist-info/top_level.txt
zedblock_client-1.0.0.dist-info/RECORD
