Metadata-Version: 2.4
Name: zedblock_client
Version: 1.0.0
Summary: Zedblock Apis
Home-page: https://github.com/Zed-block/zedblock_client
Author: Zed-block
Author-email: info@zedblock.com
Project-URL: Source, https://github.com/Zed-block/zedblock_client
Classifier: Programming Language :: Python :: 3
Classifier: License :: OSI Approved :: MIT License
Requires-Python: >=3.8
Requires-Dist: urllib3<3.0.0,>=1.25.3
Requires-Dist: python-dateutil>=2.8.2
Requires-Dist: pydantic>=2
Requires-Dist: typing-extensions>=4.7.1
Dynamic: author
Dynamic: author-email
Dynamic: classifier
Dynamic: description
Dynamic: description-content-type
Dynamic: home-page
Dynamic: project-url
Dynamic: requires-dist
Dynamic: requires-python
Dynamic: summary
